agentgrid/__init__.py
agentgrid/cli.py
agentgrid/agents/base.py
agentgrid/agents/runner.py
agentgrid/agents/simple_openai_agent.py
agentgrid/core/__init__.py
agentgrid/core/base_protocol.py
agentgrid/core/base_protocol_adapter.py
agentgrid/core/client.py
agentgrid/core/connector.py
agentgrid/core/network.py
agentgrid/core/system_commands.py
agentgrid/launchers/__init__.py
agentgrid/launchers/discovery_connector.py
agentgrid/launchers/network_launcher.py
agentgrid/launchers/terminal_console.py
agentgrid/models/__init__.py
agentgrid/models/manifest.py
agentgrid/models/message_thread.py
agentgrid/models/messages.py
agentgrid/models/network_config.py
agentgrid/models/network_profile.py
agentgrid/models/tool.py
agentgrid/protocols/__init__.py
agentgrid/protocols/communication/__init__.py
agentgrid/protocols/communication/simple_messaging/__init__.py
agentgrid/protocols/communication/simple_messaging/adapter.py
agentgrid/protocols/communication/simple_messaging/protocol.py
agentgrid/protocols/discovery/__init__.py
agentgrid/protocols/discovery/agent_discovery/__init__.py
agentgrid/protocols/discovery/agent_discovery/adapter.py
agentgrid/protocols/discovery/agent_discovery/protocol.py
agentgrid/utils/__init__.py
agentgrid/utils/message_util.py
agentgrid/utils/network_discovey.py
agentgrid/utils/protocol_loaders.py
agentgrid-0.4.0.dist-info/licenses/LICENSE
openagents/__init__.py
openagents/cli.py
openagents/agents/base.py
openagents/agents/runner.py
openagents/agents/simple_openai_agent.py
openagents/core/__init__.py
openagents/core/base_protocol.py
openagents/core/base_protocol_adapter.py
openagents/core/client.py
openagents/core/connector.py
openagents/core/network.py
openagents/core/system_commands.py
openagents/launchers/__init__.py
openagents/launchers/discovery_connector.py
openagents/launchers/network_launcher.py
openagents/launchers/terminal_console.py
openagents/models/__init__.py
openagents/models/manifest.py
openagents/models/message_thread.py
openagents/models/messages.py
agentgrid-0.4.0.dist-info/METADATA
agentgrid-0.4.0.dist-info/WHEEL
agentgrid-0.4.0.dist-info/entry_points.txt
agentgrid-0.4.0.dist-info/top_level.txt
agentgrid-0.4.0.dist-info/RECORD
